<?xml version="1.0" encoding="utf-8"?>
<!-- Created by ModBuddy on 7/12/2014 7:52:40 PM -->
<GameData>

	<IconTextureAtlases>
		<Row>
			<Atlas>MA_UNIVERSITY_ATLAS</Atlas>
			<IconSize>256</IconSize>
			<Filename>U_IconAtlas256.dds</Filename>
			<IconsPerRow>4</IconsPerRow>
			<IconsPerColumn>2</IconsPerColumn>
		</Row>
		<Row>
			<Atlas>MA_UNIVERSITY_ATLAS</Atlas>
			<IconSize>128</IconSize>
			<Filename>U_IconAtlas128.dds</Filename>
			<IconsPerRow>4</IconsPerRow>
			<IconsPerColumn>2</IconsPerColumn>
		</Row>
		<Row>
			<Atlas>MA_UNIVERSITY_ATLAS</Atlas>
			<IconSize>80</IconSize>
			<Filename>U_IconAtlas80.dds</Filename>
			<IconsPerRow>4</IconsPerRow>
			<IconsPerColumn>2</IconsPerColumn>
		</Row>
		<Row>
			<Atlas>MA_UNIVERSITY_ATLAS</Atlas>
			<IconSize>64</IconSize>
			<Filename>U_IconAtlas64.dds</Filename>
			<IconsPerRow>4</IconsPerRow>
			<IconsPerColumn>2</IconsPerColumn>
		</Row>
		<Row>
			<Atlas>MA_UNIVERSITY_ATLAS</Atlas>
			<IconSize>45</IconSize>
			<Filename>U_IconAtlas45.dds</Filename>
			<IconsPerRow>4</IconsPerRow>
			<IconsPerColumn>2</IconsPerColumn>
		</Row>
	</IconTextureAtlases>
  
</GameData>